matrix_operations/__init__.py
matrix_operations/operations.py
loserchen_4_lesson_matrix_operations-1.0.1.dist-info/LICENSE
loserchen_4_lesson_matrix_operations-1.0.1.dist-info/METADATA
loserchen_4_lesson_matrix_operations-1.0.1.dist-info/WHEEL
loserchen_4_lesson_matrix_operations-1.0.1.dist-info/entry_points.txt
loserchen_4_lesson_matrix_operations-1.0.1.dist-info/top_level.txt
loserchen_4_lesson_matrix_operations-1.0.1.dist-info/RECORD
