Metadata-Version: 2.1
Name: loserchen_4_lesson_matrix_operations
Version: 1.0.1
Summary: A simple package for matrix operations
Home-page: http://www.example.com
Author: Your Name
Author-email: your.email@example.com
Classifier: Programming Language :: Python :: 3
Classifier: License :: OSI Approved :: MIT License
Classifier: Operating System :: OS Independent
Requires-Python: >=3.6
License-File: LICENSE
Provides-Extra: dev
Requires-Dist: check-manifest; extra == "dev"
Provides-Extra: test
Requires-Dist: coverage; extra == "test"
